iloscar_win/__init__.py
iloscar_win/app.py
iloscar_win/iLOSCAR_backend.py
iloscar_win/style.py
iloscar_win/pages/Function.py
iloscar_win/pages/forward.py
iloscar_win/pages/home.py
iloscar_win/pages/inverse.py
iloscar_win-0.1.7.dist-info/METADATA
iloscar_win-0.1.7.dist-info/WHEEL
iloscar_win-0.1.7.dist-info/top_level.txt
iloscar_win-0.1.7.dist-info/RECORD
