Metadata-Version: 2.1
Name: iloscar-win
Version: 0.1.7
Summary: iLOSCAR_win
Home-page: https://github.com/Shihan150/iloscar
Author: Shihan Li
Author-email: <shihan@tamu.edu>
License: MIT
Keywords: python,carbon cycle,model,paleoclimate,global warming,LOSCAR
Classifier: Development Status :: 3 - Alpha
Classifier: Intended Audience :: Developers
Classifier: Programming Language :: Python :: 3
Classifier: Operating System :: Microsoft :: Windows
Requires-Python: >3.7, <3.11
Requires-Dist: numpy
Requires-Dist: scipy
Requires-Dist: dash
Requires-Dist: plotly
Requires-Dist: pandas
Requires-Dist: numba
Requires-Dist: diskcache
Requires-Dist: statsmodels
Requires-Dist: dash-bootstrap-components
Requires-Dist: dash-extensions
Requires-Dist: dash[diskcache]
Requires-Dist: dill (==0.3.5.1)
